{"__symbolic":"module","version":4,"metadata":{"NgcatalystService":{"__symbolic":"class","decorators":[{"__symbolic":"call","expression":{"__symbolic":"reference","module":"@angular/core","name":"Injectable","line":2,"character":1},"arguments":[{"providedIn":"root"}]}],"members":{"__ctor__":[{"__symbolic":"constructor"}]},"statics":{"ngInjectableDef":{}}},"NgcatalystComponent":{"__symbolic":"class","decorators":[{"__symbolic":"call","expression":{"__symbolic":"reference","module":"@angular/core","name":"Component","line":2,"character":1},"arguments":[{"selector":"eikos-ngcatalyst","template":"\n    <p>\n      ngcatalyst works!\n    </p>\n  ","styles":[]}]}],"members":{"__ctor__":[{"__symbolic":"constructor"}],"ngOnInit":[{"__symbolic":"method"}]}},"NgcatalystModule":{"__symbolic":"class","decorators":[{"__symbolic":"call","expression":{"__symbolic":"reference","module":"@angular/core","name":"NgModule","line":9,"character":1},"arguments":[{"declarations":[{"__symbolic":"reference","name":"NgcatalystComponent"},{"__symbolic":"reference","name":"BarChartComponent"},{"__symbolic":"reference","name":"BubbleChartComponent"},{"__symbolic":"reference","name":"LinePlotComponent"},{"__symbolic":"reference","name":"PieChartComponent"},{"__symbolic":"reference","name":"PunchCardComponent"},{"__symbolic":"reference","name":"SunburstComponent"}],"imports":[],"exports":[{"__symbolic":"reference","name":"NgcatalystComponent"},{"__symbolic":"reference","name":"BarChartComponent"},{"__symbolic":"reference","name":"BubbleChartComponent"},{"__symbolic":"reference","name":"LinePlotComponent"},{"__symbolic":"reference","name":"PieChartComponent"},{"__symbolic":"reference","name":"PunchCardComponent"},{"__symbolic":"reference","name":"SunburstComponent"}]}]}],"members":{}},"BarChartComponent":{"__symbolic":"class","decorators":[{"__symbolic":"call","expression":{"__symbolic":"reference","module":"@angular/core","name":"Component","line":3,"character":1},"arguments":[{"selector":"eikos-bar-chart","template":"\n  <h2>{{title}}</h2>\n    <div style=\"height: 750px; width: 750px;\" >\n      <div [id]=\"propID\" style=\"width:100%;height:100%\">\n      </div>\n    </div>\n  "}]}],"members":{"data":[{"__symbolic":"property","decorators":[{"__symbolic":"call","expression":{"__symbolic":"reference","module":"@angular/core","name":"Input","line":14,"character":3}}]}],"propID":[{"__symbolic":"property","decorators":[{"__symbolic":"call","expression":{"__symbolic":"reference","module":"@angular/core","name":"Input","line":15,"character":3}}]}],"color":[{"__symbolic":"property","decorators":[{"__symbolic":"call","expression":{"__symbolic":"reference","module":"@angular/core","name":"Input","line":16,"character":3}}]}],"yAxisLabel":[{"__symbolic":"property","decorators":[{"__symbolic":"call","expression":{"__symbolic":"reference","module":"@angular/core","name":"Input","line":17,"character":3}}]}],"xAxisLabel":[{"__symbolic":"property","decorators":[{"__symbolic":"call","expression":{"__symbolic":"reference","module":"@angular/core","name":"Input","line":18,"character":3}}]}],"xAxisAngle":[{"__symbolic":"property","decorators":[{"__symbolic":"call","expression":{"__symbolic":"reference","module":"@angular/core","name":"Input","line":19,"character":3}}]}],"yAxisAngle":[{"__symbolic":"property","decorators":[{"__symbolic":"call","expression":{"__symbolic":"reference","module":"@angular/core","name":"Input","line":20,"character":3}}]}],"title":[{"__symbolic":"property","decorators":[{"__symbolic":"call","expression":{"__symbolic":"reference","module":"@angular/core","name":"Input","line":21,"character":3}}]}],"__ctor__":[{"__symbolic":"constructor"}],"ngAfterViewInit":[{"__symbolic":"method"}],"ngOnChanges":[{"__symbolic":"method"}],"mouseover_callback":[{"__symbolic":"method"}],"drawBarPlot":[{"__symbolic":"method"}]}},"BubbleChartComponent":{"__symbolic":"class","decorators":[{"__symbolic":"call","expression":{"__symbolic":"reference","module":"@angular/core","name":"Component","line":4,"character":1},"arguments":[{"selector":"eikos-bubble-chart","template":"\n<h2>{{title}}</h2>\n<div style=\"height: 750px; width: 750px;\" >\n    <div [id]=\"propID\" style=\"width:100%;height:100%\"> </div>\n</div>\n  "}]}],"members":{"propID":[{"__symbolic":"property","decorators":[{"__symbolic":"call","expression":{"__symbolic":"reference","module":"@angular/core","name":"Input","line":15,"character":3}}]}],"data":[{"__symbolic":"property","decorators":[{"__symbolic":"call","expression":{"__symbolic":"reference","module":"@angular/core","name":"Input","line":16,"character":3}}]}],"title":[{"__symbolic":"property","decorators":[{"__symbolic":"call","expression":{"__symbolic":"reference","module":"@angular/core","name":"Input","line":17,"character":3}}]}],"isTime":[{"__symbolic":"property","decorators":[{"__symbolic":"call","expression":{"__symbolic":"reference","module":"@angular/core","name":"Input","line":18,"character":3}}]}],"isDate":[{"__symbolic":"property","decorators":[{"__symbolic":"call","expression":{"__symbolic":"reference","module":"@angular/core","name":"Input","line":19,"character":3}}]}],"themeColors":[{"__symbolic":"property","decorators":[{"__symbolic":"call","expression":{"__symbolic":"reference","module":"@angular/core","name":"Input","line":20,"character":3}}]}],"yAxisLabel":[{"__symbolic":"property","decorators":[{"__symbolic":"call","expression":{"__symbolic":"reference","module":"@angular/core","name":"Input","line":22,"character":3}}]}],"xAxisLabel":[{"__symbolic":"property","decorators":[{"__symbolic":"call","expression":{"__symbolic":"reference","module":"@angular/core","name":"Input","line":23,"character":3}}]}],"__ctor__":[{"__symbolic":"constructor"}],"ngOnInit":[{"__symbolic":"method"}],"ngOnChanges":[{"__symbolic":"method"}],"ngAfterViewInit":[{"__symbolic":"method"}],"xValue":[{"__symbolic":"method"}],"yValue":[{"__symbolic":"method"}],"zValue":[{"__symbolic":"method"}],"pretty_duration":[{"__symbolic":"method"}],"get_min_bubble_size":[{"__symbolic":"method"}],"get_max_bubble_size":[{"__symbolic":"method"}],"get_bubble_sizes":[{"__symbolic":"method"}],"get_duration_zoom_range":[{"__symbolic":"method"}],"get_x_zoom_range":[{"__symbolic":"method"}],"drawBubbleChart":[{"__symbolic":"method"}]}},"LinePlotComponent":{"__symbolic":"class","decorators":[{"__symbolic":"call","expression":{"__symbolic":"reference","module":"@angular/core","name":"Component","line":3,"character":1},"arguments":[{"selector":"eikos-line-plot","template":"\n  <h2>{{title}}</h2>\n  <div style=\"height: 750px; width: 750px;\" >\n      <div [id]=\"propID\" style=\"width:100%;height:100%\"> </div>\n  </div>\n"}]}],"members":{"propID":[{"__symbolic":"property","decorators":[{"__symbolic":"call","expression":{"__symbolic":"reference","module":"@angular/core","name":"Input","line":14,"character":3}}]}],"data":[{"__symbolic":"property","decorators":[{"__symbolic":"call","expression":{"__symbolic":"reference","module":"@angular/core","name":"Input","line":15,"character":3}}]}],"title":[{"__symbolic":"property","decorators":[{"__symbolic":"call","expression":{"__symbolic":"reference","module":"@angular/core","name":"Input","line":16,"character":3}}]}],"color":[{"__symbolic":"property","decorators":[{"__symbolic":"call","expression":{"__symbolic":"reference","module":"@angular/core","name":"Input","line":17,"character":3}}]}],"yAxisLabel":[{"__symbolic":"property","decorators":[{"__symbolic":"call","expression":{"__symbolic":"reference","module":"@angular/core","name":"Input","line":18,"character":3}}]}],"xAxisLabel":[{"__symbolic":"property","decorators":[{"__symbolic":"call","expression":{"__symbolic":"reference","module":"@angular/core","name":"Input","line":19,"character":3}}]}],"__ctor__":[{"__symbolic":"constructor"}],"ngOnInit":[{"__symbolic":"method"}],"ngOnChanges":[{"__symbolic":"method"}],"ngAfterViewInit":[{"__symbolic":"method"}],"drawLinePlot":[{"__symbolic":"method"}]}},"PieChartComponent":{"__symbolic":"class","decorators":[{"__symbolic":"call","expression":{"__symbolic":"reference","module":"@angular/core","name":"Component","line":3,"character":1},"arguments":[{"selector":"eikos-pie-chart","template":"\n  <h2>{{title}}</h2>\n  <div style=\"height: 750px; width: 750px;\" >\n      <div [id]=\"propID\" style=\"width:100%;height:100%\"> </div>\n  </div>\n"}]}],"members":{"propID":[{"__symbolic":"property","decorators":[{"__symbolic":"call","expression":{"__symbolic":"reference","module":"@angular/core","name":"Input","line":14,"character":3}}]}],"data":[{"__symbolic":"property","decorators":[{"__symbolic":"call","expression":{"__symbolic":"reference","module":"@angular/core","name":"Input","line":15,"character":3}}]}],"title":[{"__symbolic":"property","decorators":[{"__symbolic":"call","expression":{"__symbolic":"reference","module":"@angular/core","name":"Input","line":16,"character":3}}]}],"donutWidth":[{"__symbolic":"property","decorators":[{"__symbolic":"call","expression":{"__symbolic":"reference","module":"@angular/core","name":"Input","line":17,"character":3}}]}],"colors":[{"__symbolic":"property","decorators":[{"__symbolic":"call","expression":{"__symbolic":"reference","module":"@angular/core","name":"Input","line":18,"character":3}}]}],"__ctor__":[{"__symbolic":"constructor"}],"ngOnInit":[{"__symbolic":"method"}],"ngOnChanges":[{"__symbolic":"method"}],"ngAfterViewInit":[{"__symbolic":"method"}],"drawPieChart":[{"__symbolic":"method"}]}},"PunchCardComponent":{"__symbolic":"class","decorators":[{"__symbolic":"call","expression":{"__symbolic":"reference","module":"@angular/core","name":"Component","line":4,"character":1},"arguments":[{"selector":"eikos-punch-card","styles":["\n    .punch-border {\n      stroke: grey\n    }\n  "],"template":"\n  <h2>{{title}}</h2>\n  <div style=\"height: 750px; width: 1500px; margin-left: 3%\" >\n      <div [id]=\"propID\" style=\"width:100%;height:100%\"> </div>\n  </div>\n"}]}],"members":{"propID":[{"__symbolic":"property","decorators":[{"__symbolic":"call","expression":{"__symbolic":"reference","module":"@angular/core","name":"Input","line":20,"character":3}}]}],"data":[{"__symbolic":"property","decorators":[{"__symbolic":"call","expression":{"__symbolic":"reference","module":"@angular/core","name":"Input","line":21,"character":3}}]}],"title":[{"__symbolic":"property","decorators":[{"__symbolic":"call","expression":{"__symbolic":"reference","module":"@angular/core","name":"Input","line":22,"character":3}}]}],"axisColors":[{"__symbolic":"property","decorators":[{"__symbolic":"call","expression":{"__symbolic":"reference","module":"@angular/core","name":"Input","line":23,"character":3}}]}],"axisLabel":[{"__symbolic":"property","decorators":[{"__symbolic":"call","expression":{"__symbolic":"reference","module":"@angular/core","name":"Input","line":24,"character":3}}]}],"colors":[{"__symbolic":"property","decorators":[{"__symbolic":"call","expression":{"__symbolic":"reference","module":"@angular/core","name":"Input","line":25,"character":3}}]}],"__ctor__":[{"__symbolic":"constructor"}],"ngOnInit":[{"__symbolic":"method"}],"ngOnChanges":[{"__symbolic":"method"}],"ngAfterViewInit":[{"__symbolic":"method"}],"getDay":[{"__symbolic":"method"}],"getDayName":[{"__symbolic":"method"}],"drawPunchCard":[{"__symbolic":"method"}]}},"SunburstComponent":{"__symbolic":"class","decorators":[{"__symbolic":"call","expression":{"__symbolic":"reference","module":"@angular/core","name":"Component","line":3,"character":1},"arguments":[{"selector":"eikos-sunburst","template":"\n  <h2>{{title}}</h2>\n  <div style=\"height: 750px; width: 750px;\" >\n      <div [id]=\"propID\" style=\"width:100%;height:100%\"> </div>\n  </div>\n"}]}],"members":{"propID":[{"__symbolic":"property","decorators":[{"__symbolic":"call","expression":{"__symbolic":"reference","module":"@angular/core","name":"Input","line":14,"character":3}}]}],"data":[{"__symbolic":"property","decorators":[{"__symbolic":"call","expression":{"__symbolic":"reference","module":"@angular/core","name":"Input","line":15,"character":3}}]}],"title":[{"__symbolic":"property","decorators":[{"__symbolic":"call","expression":{"__symbolic":"reference","module":"@angular/core","name":"Input","line":16,"character":3}}]}],"__ctor__":[{"__symbolic":"constructor"}],"ngOnInit":[{"__symbolic":"method"}],"ngOnChanges":[{"__symbolic":"method"}],"ngAfterViewInit":[{"__symbolic":"method"}],"drawSunburst":[{"__symbolic":"method"}]}}},"origins":{"NgcatalystService":"./lib/ngcatalyst.service","NgcatalystComponent":"./lib/ngcatalyst.component","NgcatalystModule":"./lib/ngcatalyst.module","BarChartComponent":"./lib/bar-chart.component","BubbleChartComponent":"./lib/bubble-chart.component","LinePlotComponent":"./lib/line-plot.component","PieChartComponent":"./lib/pie-chart.component","PunchCardComponent":"./lib/punch-card.component","SunburstComponent":"./lib/sunburst.component"},"importAs":"ngcatalyst"}